odoo/addons/stock_picking_show_backorder/README.rst
odoo/addons/stock_picking_show_backorder/__init__.py
odoo/addons/stock_picking_show_backorder/__manifest__.py
odoo/addons/stock_picking_show_backorder/i18n/cs_CZ.po
odoo/addons/stock_picking_show_backorder/i18n/de.po
odoo/addons/stock_picking_show_backorder/i18n/es.po
odoo/addons/stock_picking_show_backorder/i18n/fr.po
odoo/addons/stock_picking_show_backorder/i18n/it.po
odoo/addons/stock_picking_show_backorder/i18n/nl_NL.po
odoo/addons/stock_picking_show_backorder/i18n/pt.po
odoo/addons/stock_picking_show_backorder/i18n/pt_BR.po
odoo/addons/stock_picking_show_backorder/i18n/sl.po
odoo/addons/stock_picking_show_backorder/i18n/stock_picking_show_backorder.pot
odoo/addons/stock_picking_show_backorder/models/__init__.py
odoo/addons/stock_picking_show_backorder/models/stock.py
odoo/addons/stock_picking_show_backorder/readme/CONTRIBUTORS.rst
odoo/addons/stock_picking_show_backorder/readme/DESCRIPTION.rst
odoo/addons/stock_picking_show_backorder/readme/USAGE.rst
odoo/addons/stock_picking_show_backorder/static/description/icon.png
odoo/addons/stock_picking_show_backorder/static/description/index.html
odoo/addons/stock_picking_show_backorder/tests/__init__.py
odoo/addons/stock_picking_show_backorder/tests/test_stock_picking_show_backorder.py
odoo/addons/stock_picking_show_backorder/views/stock_view.xml
odoo14_addon_stock_picking_show_backorder-14.0.1.0.1.dev9.dist-info/METADATA
odoo14_addon_stock_picking_show_backorder-14.0.1.0.1.dev9.dist-info/WHEEL
odoo14_addon_stock_picking_show_backorder-14.0.1.0.1.dev9.dist-info/top_level.txt
odoo14_addon_stock_picking_show_backorder-14.0.1.0.1.dev9.dist-info/RECORD
