Metadata-Version: 2.1
Name: odoo14-addon-stock_picking_show_backorder
Version: 14.0.1.0.1.dev9
Summary: Provides a new field on stock pickings, allowing to display the corresponding backorders.
Home-page: https://github.com/OCA/stock-logistics-workflow
Author: Eficent, Odoo Community Association (OCA)
Author-email: support@odoo-community.org
License: AGPL-3
Classifier: Programming Language :: Python
Classifier: Framework :: Odoo
Classifier: Framework :: Odoo :: 14.0
Classifier: License :: OSI Approved :: GNU Affero General Public License v3
Requires-Python: >=3.6
Requires-Dist: odoo<14.1dev,>=14.0a
